smart_pyxl/__init__.py
smart_pyxl/file.py
smart_pyxl/sheet.py
smart_pyxl-0.1.0.dist-info/LICENSE.txt
smart_pyxl-0.1.0.dist-info/METADATA
smart_pyxl-0.1.0.dist-info/WHEEL
smart_pyxl-0.1.0.dist-info/top_level.txt
smart_pyxl-0.1.0.dist-info/RECORD
