Metadata-Version: 2.2
Name: smart_pyxl
Version: 0.1.0
License: This software is under the MIT Licence
License-File: LICENSE.txt
Requires-Dist: pandas>=2.2.3
Requires-Dist: openpyxl>=3.1.0
